<?xml version="1.0" encoding="UTF-8"?>
<lido:lido xmlns:gml="http://www.opengis.net/gml"
           xmlns:lido="http://www.lido-schema.org"
           xmlns:xsi="http://www.w3.org/2001/XMLSchema-instance">
   <lido:lidoRecID lido:source="https://berlin.museum-digital.de/index.php?t=institution&amp;instnr=21"
                   lido:type="local">DE-MUS-061525/86350</lido:lidoRecID>
   <lido:descriptiveMetadata xml:lang="de">
      <lido:objectClassificationWrap>
         <lido:objectWorkTypeWrap>
            <lido:objectWorkType>
               <lido:conceptID lido:source="gnd" lido:type="uri">http://d-nb.info/gnd/4164176-0</lido:conceptID>
               <lido:conceptID lido:source="grobsystematik" lido:type="uri">https://term.museum-digital.de/grobsystematik/tag/13321</lido:conceptID>
               <lido:conceptID lido:source="oberbegriffsdatei" lido:type="uri">https://term.museum-digital.de/oberbegriffsdatei/tag/2036</lido:conceptID>
               <lido:conceptID lido:source="aat" lido:type="uri">http://vocab.getty.edu/aat/300041575</lido:conceptID>
               <lido:conceptID lido:source="lcsh" lido:type="uri">http://id.loc.gov/authorities/subjects/sh85027100</lido:conceptID>
               <lido:conceptID lido:source="md:term" lido:type="uri">https://term.museum-digital.de/md-de/tag/1331</lido:conceptID>
               <lido:term>Uhr</lido:term>
            </lido:objectWorkType>
         </lido:objectWorkTypeWrap>
         <lido:classificationWrap>
            <lido:classification lido:type="Sammlung">
               <lido:conceptID lido:source="local" lido:type="collection_id">623</lido:conceptID>
               <lido:term lido:addedSearchTerm="no">Uhrensammlung</lido:term>
            </lido:classification>
         </lido:classificationWrap>
      </lido:objectClassificationWrap>
      <lido:objectIdentificationWrap>
         <lido:titleWrap>
            <lido:titleSet>
               <lido:appellationValue lido:pref="preferred">Johannes Hartmann, Konsoluhr, spätes 19. Jahrhundert, Inv. Nr. II 95/26 i</lido:appellationValue>
            </lido:titleSet>
         </lido:titleWrap>
         <lido:inscriptionsWrap>
            <lido:inscriptions>
               <lido:inscriptionDescription>
                  <lido:descriptiveNoteValue>Joh.s HARTMANN Kgl. Hofuhrmacher BERLIN</lido:descriptiveNoteValue>
               </lido:inscriptionDescription>
            </lido:inscriptions>
         </lido:inscriptionsWrap>
         <lido:repositoryWrap>
            <lido:repositorySet lido:type="current">
               <lido:repositoryName>
                  <lido:legalBodyID lido:type="isil">DE-MUS-061525</lido:legalBodyID>
                  <lido:legalBodyName>
                     <lido:appellationValue>Stiftung Stadtmuseum Berlin</lido:appellationValue>
                  </lido:legalBodyName>
                  <lido:legalBodyWeblink>https://www.stadtmuseum.de</lido:legalBodyWeblink>
               </lido:repositoryName>
               <lido:workID lido:type="inventory number">II 95/26 i</lido:workID>
               <lido:repositoryLocation>
                  <lido:namePlaceSet>
                     <lido:appellationValue>Berlin</lido:appellationValue>
                  </lido:namePlaceSet>
                  <lido:gml>
                     <gml:Point srsName="EPSG:4326">
                        <gml:pos>52.51618576 13.40692997</gml:pos>
                     </gml:Point>
                  </lido:gml>
               </lido:repositoryLocation>
            </lido:repositorySet>
         </lido:repositoryWrap>
         <lido:objectDescriptionWrap>
            <lido:objectDescriptionSet>
               <lido:descriptiveNoteValue>Diese Konsoluhr des späten 19. Jahrhunderts folgt dem Vorbild französischer Louis XV.-Pendulen aus der Mitte des 18. Jahrhunderts und war in ihrer Zeit vermutlich ein kostbares Ausstattungsstück für einen begüterten Berliner Bürger. Sowohl Gehäuse als auch Wandkonsole sind reich mit rötlichem Schildpattimitat und Messingintarsien ausgelegt. Die vergoldeten Bronzen in Form von rankenden Pflanzen mit Blüten wurden an allen seitlichen Kanten, aber auch flächig montiert. Unten enden diese in sich nach außen rollenden Füßen. Oben der Baldachin, der nicht abnehmbar ist, wird von einer sich wild nach oben schlängelnder Blattpflanze bekrönt. Ursprünglich verbarg sich unter den abnehmbaren Baldachinen bei Uhren des 18. Jahrhunderts die Bronzeglocke. Hier wurde die Glocke hinten am Uhrwerk montiert, wie es bei den französischen Werken von Japy üblich ist. Die Bronzen an der Konsole, die sich nach unten schwungvoll verjüngt, enden in einer stilisierten Muschel. Die Messingintarsien sind zudem reich graviert und mit Gravurkitt ausgelegt. Auch das Zifferblatt wurde nach den Uhren des 18. Jahrhunderts gestaltet, in der Art Treize pièces, jedoch in einem Stück gefertigt.&lt;br&gt;
Das Stadtmuseum besitzt drei weitere Kaminuhren von Johannes Hartmann, die auf den ersten Blick alle in der sogenannten Boulle-Technik gearbeitet wurden. Diese gelten als hochwertige Schildpattarbeiten. Franka Görike stellte jedoch 2009 mit Hilfe einer Analyse fest, dass es sich bei dem hier verwendeten Material um ein Surrogat handelt, das farbig hinterlegt ist, um den Eindruck von Schildpatt zu erwecken. In der historischen Literatur wird der Herstellungsprozess von Schildpatt-Imitationen genauestens beschrieben. Ab der Mitte des 19. Jahrhunderts versuchte man, kostbare Materialien durch Imitationen zu ersetzen, um den Konsum von Luxusgütern auch Menschen mit kleinerem Geldbeutel zu ermöglichen. Es ist bisher nicht bekannt, wo die Gehäuse gefertigt wurden. Nachweislich existierte in Berlin in dieser Zeit die hervorragende Intarsien-Werkstatt Nast, die zum Beispiel für die Herstellung in Frage käme. Der Grundkorpus der Gehäuse ist sehr robust, die Einlegearbeiten äußerst fein gearbeitet. Eine Kaminuhr auf einem Sockel, ebenfalls von Hartmann, die im Knoblauchhaus in Berlin ausgestellt ist, wurde 2009 restauriert und in diesem Zusammenhang die Analyse durchgeführt. Beide Uhren besitzen ein Japy-Uhrwerk. Zwei weitere Kaminuhren, die mit einer Höhe von fast 80 cm sehr groß sind, besitzen ein quadratisches Uhrwerk, das Hartmann häufig benutzte. Auch bei diesen beiden Uhren wurde das Surrogat mit rot gefärbtem Papier unterlegt. Es ist zu vermuten, dass alle Uhren von Hartmann in „Boulle-Technik“ mit einem Schildpattsurrogat ausgestattet wurden. Papieraufkleber an seinen Uhren zeigen, dass Hartmann sich auch als Uhrenfabrikant bezeichnete. &lt;br&gt;
Die Firmengeschichte Johannes Hartmanns beginnt mit der Firmengründung von Georg Nevir 1763, Hofuhrmacher von Friedrich dem Großen, der nach 1800 das Geschäft an Benjamin Friedrich Schunigk übergab. Nach dessen Tode übernahm Nevirs Sohn Dominique wieder die Firma und veräußerte diese 1856 an Johannes Hartmann, der sie bis 1872 weiterführte. Die Firma bestand bis 1938 unter dem Namen „Joh.s Hartmann vorm. D. Nevir“ weiter.&lt;br&gt;
Das Stadtmuseum Berlin kaufte die Uhr 1995 vom Uhrenrestaurator Jörg Hein, Berlin. (Marina de Fümel)&lt;br&gt;</lido:descriptiveNoteValue>
               <lido:sourceDescriptiveNote>Stiftung Stadtmuseum Berlin</lido:sourceDescriptiveNote>
            </lido:objectDescriptionSet>
            <lido:objectDescriptionSet lido:type="Detailbeschreibung">
               <lido:descriptiveNoteValue>Das runde Vollplatinenwerk (D: 8 cm, schlichte zylindrische Werkpfeiler-H: 3,1 cm) besitzt eine Clementhemmung, ein Rechenschlagwerk mit Halbstundenschlag auf eine Bronzeglocke, eine Pendelfederaufhängung für das Pendel, das von vorn über der arabischen Minutenzahl „60“ durch eine Achse zur Pendelaufhängung reguliert werden kann. Der Aufzug erfolgt von vorn bei den Ziffern IIII und VIII. Das Emailzifferblatt (D: 10,8 cm) mit den segmentierten römischen Stundenzahlen, der Minuterie in Strichen und Punkten und den darüber angeordneten arabischen Minutenangaben in Fünferschritten zeigt in der Mitte oben und unten die Signatur JOH.s HARTMANN Kgl. Hofuhrmacher BERLIN. Die gebläuten Stahlzeiger sind typisch für die Zeit um 1870 bis 1900.&lt;br&gt;
Auf der Rückplatine (Platinenstärke: 0,2 cm) gibt es verschiedene Stempel, links im Oval „B &amp; G“, unten mittig „Medaille d‘ Argent S. Marti et Cie“, daneben „JH“ und die Jahreszahlen 1972, 1983, 1993, darunter die Werknummer 7017. Der Stempel JH steht für den Vorbesitzer Jörg Hein, der beim Staatlichen Kunsthandel der DDR Restaurator war. Die darauf folgenden Jahreszahlen verweisen auf das Jahr einer Reparatur. Die Signatur „B &amp; G“ konnte nicht identifiziert werden. Die Silber-Medaille verweist auf die Firma Samuel Marti &amp; Cie Paris, um 1889. Demnach könnte das Rohwerk etwa in dieser Zeit von der Firma Hartmann in Frankreich angekauft und nach eigenen Vorstellungen in der Berliner Werkstatt umgearbeitet worden sein. Johannes Hartmann hatte zwar sein Geschäft 1872 an H. A. Markfeldt weitergegeben, doch dieser führte es unter demselben Namen bzw. mit „Joh.s Hartmann vorm. Nevir“ weiter. Vermutlich benutzte er auch weiterhin die Bezeichnung „Kgl. Hofuhrmacher“. (Marina de Fümel)</lido:descriptiveNoteValue>
               <lido:sourceDescriptiveNote>Stiftung Stadtmuseum Berlin</lido:sourceDescriptiveNote>
            </lido:objectDescriptionSet>
         </lido:objectDescriptionWrap>
         <lido:objectMeasurementsWrap>
            <lido:objectMeasurementsSet>
               <lido:displayObjectMeasurements>Gehäuse: Höhe 45,5 cm, Breite 21,3 cm, Tiefe 13 cm</lido:displayObjectMeasurements>
            </lido:objectMeasurementsSet>
         </lido:objectMeasurementsWrap>
      </lido:objectIdentificationWrap>
      <lido:eventWrap>
         <lido:eventSet>
            <lido:displayEvent>Hergestellt</lido:displayEvent>
            <lido:event>
               <lido:eventType>
                  <lido:conceptID lido:type="uri">http://terminology.lido-schema.org/lido00007</lido:conceptID>
                  <lido:term lido:addedSearchTerm="no">Hergestellt</lido:term>
               </lido:eventType>
               <lido:eventActor>
                  <lido:displayActorInRole>Johannes Hartmann</lido:displayActorInRole>
                  <lido:actorInRole>
                     <lido:actor>
                        <lido:actorID lido:source="md:term" lido:type="uri">https://term.museum-digital.de/md-de/persinst/152349</lido:actorID>
                        <lido:nameActorSet>
                           <lido:appellationValue>Hartmann, Johannes</lido:appellationValue>
                        </lido:nameActorSet>
                     </lido:actor>
                  </lido:actorInRole>
               </lido:eventActor>
               <lido:eventDate>
                  <lido:displayDate>Ende 19. Jahrhundert</lido:displayDate>
                  <lido:date>
                     <lido:earliestDate>1880</lido:earliestDate>
                     <lido:latestDate>1899</lido:latestDate>
                  </lido:date>
               </lido:eventDate>
               <lido:eventPlace>
                  <lido:displayPlace>Berlin</lido:displayPlace>
                  <lido:displayPlace xml:lang="ar">برلين</lido:displayPlace>
                  <lido:displayPlace xml:lang="bn">বার্লিন</lido:displayPlace>
                  <lido:displayPlace xml:lang="cs">Berlín</lido:displayPlace>
                  <lido:displayPlace xml:lang="da">Berlin</lido:displayPlace>
                  <lido:displayPlace xml:lang="el">Βερολίνο</lido:displayPlace>
                  <lido:displayPlace xml:lang="en">Berlin</lido:displayPlace>
                  <lido:displayPlace xml:lang="es">Berlín</lido:displayPlace>
                  <lido:displayPlace xml:lang="fa">برلین</lido:displayPlace>
                  <lido:displayPlace xml:lang="fi">Berliini</lido:displayPlace>
                  <lido:displayPlace xml:lang="fr">Berlin</lido:displayPlace>
                  <lido:displayPlace xml:lang="ha">Berlin</lido:displayPlace>
                  <lido:displayPlace xml:lang="he">ברלין</lido:displayPlace>
                  <lido:displayPlace xml:lang="hi">बर्लिन</lido:displayPlace>
                  <lido:displayPlace xml:lang="hu">Berlin</lido:displayPlace>
                  <lido:displayPlace xml:lang="id">Berlin</lido:displayPlace>
                  <lido:displayPlace xml:lang="it">Berlino</lido:displayPlace>
                  <lido:displayPlace xml:lang="ja">ベルリン</lido:displayPlace>
                  <lido:displayPlace xml:lang="ka">ბერლინი</lido:displayPlace>
                  <lido:displayPlace xml:lang="ko">베를린</lido:displayPlace>
                  <lido:displayPlace xml:lang="nl">Berlijn</lido:displayPlace>
                  <lido:displayPlace xml:lang="pl">Berlin</lido:displayPlace>
                  <lido:displayPlace xml:lang="pt">Berlim</lido:displayPlace>
                  <lido:displayPlace xml:lang="ro">Berlin</lido:displayPlace>
                  <lido:displayPlace xml:lang="ru">Берлин</lido:displayPlace>
                  <lido:displayPlace xml:lang="sv">Berlin</lido:displayPlace>
                  <lido:displayPlace xml:lang="sw">Berlin</lido:displayPlace>
                  <lido:displayPlace xml:lang="ta">பெர்லின்</lido:displayPlace>
                  <lido:displayPlace xml:lang="th">เบอร์ลิน</lido:displayPlace>
                  <lido:displayPlace xml:lang="tl">Berlin</lido:displayPlace>
                  <lido:displayPlace xml:lang="tr">Berlin</lido:displayPlace>
                  <lido:displayPlace xml:lang="ur">برلن</lido:displayPlace>
                  <lido:displayPlace xml:lang="vi">Berlin</lido:displayPlace>
                  <lido:displayPlace xml:lang="zh">柏林</lido:displayPlace>
                  <lido:place>
                     <lido:placeID lido:source="geonames" lido:type="uri">https://sws.geonames.org/2950159</lido:placeID>
                     <lido:placeID lido:source="TGN" lido:type="uri">http://vocab.getty.edu/tgn/7209904</lido:placeID>
                     <lido:placeID lido:source="gnd" lido:type="uri">https://d-nb.info/gnd/4005728-8</lido:placeID>
                     <lido:placeID lido:source="wikidata" lido:type="uri">https://www.wikidata.org/wiki/Q64</lido:placeID>
                     <lido:placeID lido:source="md:term" lido:type="uri">https://term.museum-digital.de/md-de/place/61</lido:placeID>
                     <lido:namePlaceSet>
                        <lido:appellationValue>Berlin</lido:appellationValue>
                        <lido:appellationValue xml:lang="ar">برلين</lido:appellationValue>
                        <lido:appellationValue xml:lang="bn">বার্লিন</lido:appellationValue>
                        <lido:appellationValue xml:lang="cs">Berlín</lido:appellationValue>
                        <lido:appellationValue xml:lang="da">Berlin</lido:appellationValue>
                        <lido:appellationValue xml:lang="el">Βερολίνο</lido:appellationValue>
                        <lido:appellationValue xml:lang="en">Berlin</lido:appellationValue>
                        <lido:appellationValue xml:lang="es">Berlín</lido:appellationValue>
                        <lido:appellationValue xml:lang="fa">برلین</lido:appellationValue>
                        <lido:appellationValue xml:lang="fi">Berliini</lido:appellationValue>
                        <lido:appellationValue xml:lang="fr">Berlin</lido:appellationValue>
                        <lido:appellationValue xml:lang="ha">Berlin</lido:appellationValue>
                        <lido:appellationValue xml:lang="he">ברלין</lido:appellationValue>
                        <lido:appellationValue xml:lang="hi">बर्लिन</lido:appellationValue>
                        <lido:appellationValue xml:lang="hu">Berlin</lido:appellationValue>
                        <lido:appellationValue xml:lang="id">Berlin</lido:appellationValue>
                        <lido:appellationValue xml:lang="it">Berlino</lido:appellationValue>
                        <lido:appellationValue xml:lang="ja">ベルリン</lido:appellationValue>
                        <lido:appellationValue xml:lang="ka">ბერლინი</lido:appellationValue>
                        <lido:appellationValue xml:lang="ko">베를린</lido:appellationValue>
                        <lido:appellationValue xml:lang="nl">Berlijn</lido:appellationValue>
                        <lido:appellationValue xml:lang="pl">Berlin</lido:appellationValue>
                        <lido:appellationValue xml:lang="pt">Berlim</lido:appellationValue>
                        <lido:appellationValue xml:lang="ro">Berlin</lido:appellationValue>
                        <lido:appellationValue xml:lang="ru">Берлин</lido:appellationValue>
                        <lido:appellationValue xml:lang="sv">Berlin</lido:appellationValue>
                        <lido:appellationValue xml:lang="sw">Berlin</lido:appellationValue>
                        <lido:appellationValue xml:lang="ta">பெர்லின்</lido:appellationValue>
                        <lido:appellationValue xml:lang="th">เบอร์ลิน</lido:appellationValue>
                        <lido:appellationValue xml:lang="tl">Berlin</lido:appellationValue>
                        <lido:appellationValue xml:lang="tr">Berlin</lido:appellationValue>
                        <lido:appellationValue xml:lang="ur">برلن</lido:appellationValue>
                        <lido:appellationValue xml:lang="vi">Berlin</lido:appellationValue>
                        <lido:appellationValue xml:lang="zh">柏林</lido:appellationValue>
                     </lido:namePlaceSet>
                     <lido:gml>
                        <gml:Point srsName="EPSG:4326">
                           <gml:pos>52.516666412354 13.383333206177</gml:pos>
                        </gml:Point>
                     </lido:gml>
                  </lido:place>
               </lido:eventPlace>
               <lido:eventMaterialsTech>
                  <lido:displayMaterialsTech>Holz, Schildpattsurrogat, Messing Stahl, Emaille, Bronze; galvanisch vergoldet</lido:displayMaterialsTech>
               </lido:eventMaterialsTech>
            </lido:event>
         </lido:eventSet>
         <lido:eventSet>
            <lido:displayEvent>Restauriert</lido:displayEvent>
            <lido:event>
               <lido:eventType>
                  <lido:conceptID lido:type="uri">http://terminology.lido-schema.org/lido00034</lido:conceptID>
                  <lido:term lido:addedSearchTerm="no">Restauriert</lido:term>
               </lido:eventType>
               <lido:eventActor>
                  <lido:displayActorInRole>Jörg Hein</lido:displayActorInRole>
                  <lido:actorInRole>
                     <lido:actor>
                        <lido:actorID lido:source="md:term" lido:type="uri">https://term.museum-digital.de/md-de/persinst/152350</lido:actorID>
                        <lido:nameActorSet>
                           <lido:appellationValue>Hein, Jörg</lido:appellationValue>
                        </lido:nameActorSet>
                     </lido:actor>
                  </lido:actorInRole>
               </lido:eventActor>
               <lido:eventDate>
                  <lido:displayDate>1972</lido:displayDate>
                  <lido:displayDate xml:lang="ar">1972</lido:displayDate>
                  <lido:displayDate xml:lang="en">1972</lido:displayDate>
                  <lido:displayDate xml:lang="es">1972</lido:displayDate>
                  <lido:displayDate xml:lang="fa">1972</lido:displayDate>
                  <lido:displayDate xml:lang="fr">1972</lido:displayDate>
                  <lido:displayDate xml:lang="hu">1972</lido:displayDate>
                  <lido:displayDate xml:lang="id">1972</lido:displayDate>
                  <lido:displayDate xml:lang="it">1972</lido:displayDate>
                  <lido:displayDate xml:lang="ja">1972年</lido:displayDate>
                  <lido:displayDate xml:lang="ka">1972</lido:displayDate>
                  <lido:displayDate xml:lang="ko">1972년</lido:displayDate>
                  <lido:displayDate xml:lang="pl">1972</lido:displayDate>
                  <lido:displayDate xml:lang="pt">1972</lido:displayDate>
                  <lido:displayDate xml:lang="ro">1972</lido:displayDate>
                  <lido:displayDate xml:lang="ru">1972</lido:displayDate>
                  <lido:displayDate xml:lang="ta">1972</lido:displayDate>
                  <lido:displayDate xml:lang="tl">1972</lido:displayDate>
                  <lido:displayDate xml:lang="tr">1972</lido:displayDate>
                  <lido:displayDate xml:lang="zh">1972年</lido:displayDate>
                  <lido:date>
                     <lido:earliestDate>1972</lido:earliestDate>
                     <lido:latestDate>1972</lido:latestDate>
                  </lido:date>
               </lido:eventDate>
               <lido:eventPlace>
                  <lido:displayPlace>Berlin</lido:displayPlace>
                  <lido:displayPlace xml:lang="ar">برلين</lido:displayPlace>
                  <lido:displayPlace xml:lang="bn">বার্লিন</lido:displayPlace>
                  <lido:displayPlace xml:lang="cs">Berlín</lido:displayPlace>
                  <lido:displayPlace xml:lang="da">Berlin</lido:displayPlace>
                  <lido:displayPlace xml:lang="el">Βερολίνο</lido:displayPlace>
                  <lido:displayPlace xml:lang="en">Berlin</lido:displayPlace>
                  <lido:displayPlace xml:lang="es">Berlín</lido:displayPlace>
                  <lido:displayPlace xml:lang="fa">برلین</lido:displayPlace>
                  <lido:displayPlace xml:lang="fi">Berliini</lido:displayPlace>
                  <lido:displayPlace xml:lang="fr">Berlin</lido:displayPlace>
                  <lido:displayPlace xml:lang="ha">Berlin</lido:displayPlace>
                  <lido:displayPlace xml:lang="he">ברלין</lido:displayPlace>
                  <lido:displayPlace xml:lang="hi">बर्लिन</lido:displayPlace>
                  <lido:displayPlace xml:lang="hu">Berlin</lido:displayPlace>
                  <lido:displayPlace xml:lang="id">Berlin</lido:displayPlace>
                  <lido:displayPlace xml:lang="it">Berlino</lido:displayPlace>
                  <lido:displayPlace xml:lang="ja">ベルリン</lido:displayPlace>
                  <lido:displayPlace xml:lang="ka">ბერლინი</lido:displayPlace>
                  <lido:displayPlace xml:lang="ko">베를린</lido:displayPlace>
                  <lido:displayPlace xml:lang="nl">Berlijn</lido:displayPlace>
                  <lido:displayPlace xml:lang="pl">Berlin</lido:displayPlace>
                  <lido:displayPlace xml:lang="pt">Berlim</lido:displayPlace>
                  <lido:displayPlace xml:lang="ro">Berlin</lido:displayPlace>
                  <lido:displayPlace xml:lang="ru">Берлин</lido:displayPlace>
                  <lido:displayPlace xml:lang="sv">Berlin</lido:displayPlace>
                  <lido:displayPlace xml:lang="sw">Berlin</lido:displayPlace>
                  <lido:displayPlace xml:lang="ta">பெர்லின்</lido:displayPlace>
                  <lido:displayPlace xml:lang="th">เบอร์ลิน</lido:displayPlace>
                  <lido:displayPlace xml:lang="tl">Berlin</lido:displayPlace>
                  <lido:displayPlace xml:lang="tr">Berlin</lido:displayPlace>
                  <lido:displayPlace xml:lang="ur">برلن</lido:displayPlace>
                  <lido:displayPlace xml:lang="vi">Berlin</lido:displayPlace>
                  <lido:displayPlace xml:lang="zh">柏林</lido:displayPlace>
                  <lido:place>
                     <lido:placeID lido:source="geonames" lido:type="uri">https://sws.geonames.org/2950159</lido:placeID>
                     <lido:placeID lido:source="TGN" lido:type="uri">http://vocab.getty.edu/tgn/7209904</lido:placeID>
                     <lido:placeID lido:source="gnd" lido:type="uri">https://d-nb.info/gnd/4005728-8</lido:placeID>
                     <lido:placeID lido:source="wikidata" lido:type="uri">https://www.wikidata.org/wiki/Q64</lido:placeID>
                     <lido:placeID lido:source="md:term" lido:type="uri">https://term.museum-digital.de/md-de/place/61</lido:placeID>
                     <lido:namePlaceSet>
                        <lido:appellationValue>Berlin</lido:appellationValue>
                        <lido:appellationValue xml:lang="ar">برلين</lido:appellationValue>
                        <lido:appellationValue xml:lang="bn">বার্লিন</lido:appellationValue>
                        <lido:appellationValue xml:lang="cs">Berlín</lido:appellationValue>
                        <lido:appellationValue xml:lang="da">Berlin</lido:appellationValue>
                        <lido:appellationValue xml:lang="el">Βερολίνο</lido:appellationValue>
                        <lido:appellationValue xml:lang="en">Berlin</lido:appellationValue>
                        <lido:appellationValue xml:lang="es">Berlín</lido:appellationValue>
                        <lido:appellationValue xml:lang="fa">برلین</lido:appellationValue>
                        <lido:appellationValue xml:lang="fi">Berliini</lido:appellationValue>
                        <lido:appellationValue xml:lang="fr">Berlin</lido:appellationValue>
                        <lido:appellationValue xml:lang="ha">Berlin</lido:appellationValue>
                        <lido:appellationValue xml:lang="he">ברלין</lido:appellationValue>
                        <lido:appellationValue xml:lang="hi">बर्लिन</lido:appellationValue>
                        <lido:appellationValue xml:lang="hu">Berlin</lido:appellationValue>
                        <lido:appellationValue xml:lang="id">Berlin</lido:appellationValue>
                        <lido:appellationValue xml:lang="it">Berlino</lido:appellationValue>
                        <lido:appellationValue xml:lang="ja">ベルリン</lido:appellationValue>
                        <lido:appellationValue xml:lang="ka">ბერლინი</lido:appellationValue>
                        <lido:appellationValue xml:lang="ko">베를린</lido:appellationValue>
                        <lido:appellationValue xml:lang="nl">Berlijn</lido:appellationValue>
                        <lido:appellationValue xml:lang="pl">Berlin</lido:appellationValue>
                        <lido:appellationValue xml:lang="pt">Berlim</lido:appellationValue>
                        <lido:appellationValue xml:lang="ro">Berlin</lido:appellationValue>
                        <lido:appellationValue xml:lang="ru">Берлин</lido:appellationValue>
                        <lido:appellationValue xml:lang="sv">Berlin</lido:appellationValue>
                        <lido:appellationValue xml:lang="sw">Berlin</lido:appellationValue>
                        <lido:appellationValue xml:lang="ta">பெர்லின்</lido:appellationValue>
                        <lido:appellationValue xml:lang="th">เบอร์ลิน</lido:appellationValue>
                        <lido:appellationValue xml:lang="tl">Berlin</lido:appellationValue>
                        <lido:appellationValue xml:lang="tr">Berlin</lido:appellationValue>
                        <lido:appellationValue xml:lang="ur">برلن</lido:appellationValue>
                        <lido:appellationValue xml:lang="vi">Berlin</lido:appellationValue>
                        <lido:appellationValue xml:lang="zh">柏林</lido:appellationValue>
                     </lido:namePlaceSet>
                     <lido:gml>
                        <gml:Point srsName="EPSG:4326">
                           <gml:pos>52.516666412354 13.383333206177</gml:pos>
                        </gml:Point>
                     </lido:gml>
                  </lido:place>
               </lido:eventPlace>
            </lido:event>
         </lido:eventSet>
         <lido:eventSet>
            <lido:displayEvent>Restauriert</lido:displayEvent>
            <lido:event>
               <lido:eventType>
                  <lido:conceptID lido:type="uri">http://terminology.lido-schema.org/lido00034</lido:conceptID>
                  <lido:term lido:addedSearchTerm="no">Restauriert</lido:term>
               </lido:eventType>
               <lido:eventActor>
                  <lido:displayActorInRole>Jörg Hein</lido:displayActorInRole>
                  <lido:actorInRole>
                     <lido:actor>
                        <lido:actorID lido:source="md:term" lido:type="uri">https://term.museum-digital.de/md-de/persinst/152350</lido:actorID>
                        <lido:nameActorSet>
                           <lido:appellationValue>Hein, Jörg</lido:appellationValue>
                        </lido:nameActorSet>
                     </lido:actor>
                  </lido:actorInRole>
               </lido:eventActor>
               <lido:eventDate>
                  <lido:displayDate>1983</lido:displayDate>
                  <lido:displayDate xml:lang="ar">1983</lido:displayDate>
                  <lido:displayDate xml:lang="en">1983</lido:displayDate>
                  <lido:displayDate xml:lang="es">1983</lido:displayDate>
                  <lido:displayDate xml:lang="fa">1983</lido:displayDate>
                  <lido:displayDate xml:lang="fr">1983</lido:displayDate>
                  <lido:displayDate xml:lang="hu">1983</lido:displayDate>
                  <lido:displayDate xml:lang="id">1983</lido:displayDate>
                  <lido:displayDate xml:lang="it">1983</lido:displayDate>
                  <lido:displayDate xml:lang="ja">1983年</lido:displayDate>
                  <lido:displayDate xml:lang="ka">1983</lido:displayDate>
                  <lido:displayDate xml:lang="ko">1983년</lido:displayDate>
                  <lido:displayDate xml:lang="pl">1983</lido:displayDate>
                  <lido:displayDate xml:lang="pt">1983</lido:displayDate>
                  <lido:displayDate xml:lang="ro">1983</lido:displayDate>
                  <lido:displayDate xml:lang="ru">1983</lido:displayDate>
                  <lido:displayDate xml:lang="ta">1983</lido:displayDate>
                  <lido:displayDate xml:lang="tl">1983</lido:displayDate>
                  <lido:displayDate xml:lang="tr">1983</lido:displayDate>
                  <lido:displayDate xml:lang="zh">1983年</lido:displayDate>
                  <lido:date>
                     <lido:earliestDate>1983</lido:earliestDate>
                     <lido:latestDate>1983</lido:latestDate>
                  </lido:date>
               </lido:eventDate>
               <lido:eventPlace>
                  <lido:displayPlace>Berlin</lido:displayPlace>
                  <lido:displayPlace xml:lang="ar">برلين</lido:displayPlace>
                  <lido:displayPlace xml:lang="bn">বার্লিন</lido:displayPlace>
                  <lido:displayPlace xml:lang="cs">Berlín</lido:displayPlace>
                  <lido:displayPlace xml:lang="da">Berlin</lido:displayPlace>
                  <lido:displayPlace xml:lang="el">Βερολίνο</lido:displayPlace>
                  <lido:displayPlace xml:lang="en">Berlin</lido:displayPlace>
                  <lido:displayPlace xml:lang="es">Berlín</lido:displayPlace>
                  <lido:displayPlace xml:lang="fa">برلین</lido:displayPlace>
                  <lido:displayPlace xml:lang="fi">Berliini</lido:displayPlace>
                  <lido:displayPlace xml:lang="fr">Berlin</lido:displayPlace>
                  <lido:displayPlace xml:lang="ha">Berlin</lido:displayPlace>
                  <lido:displayPlace xml:lang="he">ברלין</lido:displayPlace>
                  <lido:displayPlace xml:lang="hi">बर्लिन</lido:displayPlace>
                  <lido:displayPlace xml:lang="hu">Berlin</lido:displayPlace>
                  <lido:displayPlace xml:lang="id">Berlin</lido:displayPlace>
                  <lido:displayPlace xml:lang="it">Berlino</lido:displayPlace>
                  <lido:displayPlace xml:lang="ja">ベルリン</lido:displayPlace>
                  <lido:displayPlace xml:lang="ka">ბერლინი</lido:displayPlace>
                  <lido:displayPlace xml:lang="ko">베를린</lido:displayPlace>
                  <lido:displayPlace xml:lang="nl">Berlijn</lido:displayPlace>
                  <lido:displayPlace xml:lang="pl">Berlin</lido:displayPlace>
                  <lido:displayPlace xml:lang="pt">Berlim</lido:displayPlace>
                  <lido:displayPlace xml:lang="ro">Berlin</lido:displayPlace>
                  <lido:displayPlace xml:lang="ru">Берлин</lido:displayPlace>
                  <lido:displayPlace xml:lang="sv">Berlin</lido:displayPlace>
                  <lido:displayPlace xml:lang="sw">Berlin</lido:displayPlace>
                  <lido:displayPlace xml:lang="ta">பெர்லின்</lido:displayPlace>
                  <lido:displayPlace xml:lang="th">เบอร์ลิน</lido:displayPlace>
                  <lido:displayPlace xml:lang="tl">Berlin</lido:displayPlace>
                  <lido:displayPlace xml:lang="tr">Berlin</lido:displayPlace>
                  <lido:displayPlace xml:lang="ur">برلن</lido:displayPlace>
                  <lido:displayPlace xml:lang="vi">Berlin</lido:displayPlace>
                  <lido:displayPlace xml:lang="zh">柏林</lido:displayPlace>
                  <lido:place>
                     <lido:placeID lido:source="geonames" lido:type="uri">https://sws.geonames.org/2950159</lido:placeID>
                     <lido:placeID lido:source="TGN" lido:type="uri">http://vocab.getty.edu/tgn/7209904</lido:placeID>
                     <lido:placeID lido:source="gnd" lido:type="uri">https://d-nb.info/gnd/4005728-8</lido:placeID>
                     <lido:placeID lido:source="wikidata" lido:type="uri">https://www.wikidata.org/wiki/Q64</lido:placeID>
                     <lido:placeID lido:source="md:term" lido:type="uri">https://term.museum-digital.de/md-de/place/61</lido:placeID>
                     <lido:namePlaceSet>
                        <lido:appellationValue>Berlin</lido:appellationValue>
                        <lido:appellationValue xml:lang="ar">برلين</lido:appellationValue>
                        <lido:appellationValue xml:lang="bn">বার্লিন</lido:appellationValue>
                        <lido:appellationValue xml:lang="cs">Berlín</lido:appellationValue>
                        <lido:appellationValue xml:lang="da">Berlin</lido:appellationValue>
                        <lido:appellationValue xml:lang="el">Βερολίνο</lido:appellationValue>
                        <lido:appellationValue xml:lang="en">Berlin</lido:appellationValue>
                        <lido:appellationValue xml:lang="es">Berlín</lido:appellationValue>
                        <lido:appellationValue xml:lang="fa">برلین</lido:appellationValue>
                        <lido:appellationValue xml:lang="fi">Berliini</lido:appellationValue>
                        <lido:appellationValue xml:lang="fr">Berlin</lido:appellationValue>
                        <lido:appellationValue xml:lang="ha">Berlin</lido:appellationValue>
                        <lido:appellationValue xml:lang="he">ברלין</lido:appellationValue>
                        <lido:appellationValue xml:lang="hi">बर्लिन</lido:appellationValue>
                        <lido:appellationValue xml:lang="hu">Berlin</lido:appellationValue>
                        <lido:appellationValue xml:lang="id">Berlin</lido:appellationValue>
                        <lido:appellationValue xml:lang="it">Berlino</lido:appellationValue>
                        <lido:appellationValue xml:lang="ja">ベルリン</lido:appellationValue>
                        <lido:appellationValue xml:lang="ka">ბერლინი</lido:appellationValue>
                        <lido:appellationValue xml:lang="ko">베를린</lido:appellationValue>
                        <lido:appellationValue xml:lang="nl">Berlijn</lido:appellationValue>
                        <lido:appellationValue xml:lang="pl">Berlin</lido:appellationValue>
                        <lido:appellationValue xml:lang="pt">Berlim</lido:appellationValue>
                        <lido:appellationValue xml:lang="ro">Berlin</lido:appellationValue>
                        <lido:appellationValue xml:lang="ru">Берлин</lido:appellationValue>
                        <lido:appellationValue xml:lang="sv">Berlin</lido:appellationValue>
                        <lido:appellationValue xml:lang="sw">Berlin</lido:appellationValue>
                        <lido:appellationValue xml:lang="ta">பெர்லின்</lido:appellationValue>
                        <lido:appellationValue xml:lang="th">เบอร์ลิน</lido:appellationValue>
                        <lido:appellationValue xml:lang="tl">Berlin</lido:appellationValue>
                        <lido:appellationValue xml:lang="tr">Berlin</lido:appellationValue>
                        <lido:appellationValue xml:lang="ur">برلن</lido:appellationValue>
                        <lido:appellationValue xml:lang="vi">Berlin</lido:appellationValue>
                        <lido:appellationValue xml:lang="zh">柏林</lido:appellationValue>
                     </lido:namePlaceSet>
                     <lido:gml>
                        <gml:Point srsName="EPSG:4326">
                           <gml:pos>52.516666412354 13.383333206177</gml:pos>
                        </gml:Point>
                     </lido:gml>
                  </lido:place>
               </lido:eventPlace>
            </lido:event>
         </lido:eventSet>
         <lido:eventSet>
            <lido:displayEvent>Restauriert</lido:displayEvent>
            <lido:event>
               <lido:eventType>
                  <lido:conceptID lido:type="uri">http://terminology.lido-schema.org/lido00034</lido:conceptID>
                  <lido:term lido:addedSearchTerm="no">Restauriert</lido:term>
               </lido:eventType>
               <lido:eventActor>
                  <lido:displayActorInRole>Jörg Hein</lido:displayActorInRole>
                  <lido:actorInRole>
                     <lido:actor>
                        <lido:actorID lido:source="md:term" lido:type="uri">https://term.museum-digital.de/md-de/persinst/152350</lido:actorID>
                        <lido:nameActorSet>
                           <lido:appellationValue>Hein, Jörg</lido:appellationValue>
                        </lido:nameActorSet>
                     </lido:actor>
                  </lido:actorInRole>
               </lido:eventActor>
               <lido:eventDate>
                  <lido:displayDate>1993</lido:displayDate>
                  <lido:displayDate xml:lang="ar">1993</lido:displayDate>
                  <lido:displayDate xml:lang="en">1993</lido:displayDate>
                  <lido:displayDate xml:lang="es">1993</lido:displayDate>
                  <lido:displayDate xml:lang="fa">1993</lido:displayDate>
                  <lido:displayDate xml:lang="fr">1993</lido:displayDate>
                  <lido:displayDate xml:lang="hu">1993</lido:displayDate>
                  <lido:displayDate xml:lang="id">1993</lido:displayDate>
                  <lido:displayDate xml:lang="it">1993</lido:displayDate>
                  <lido:displayDate xml:lang="ja">1993年</lido:displayDate>
                  <lido:displayDate xml:lang="ka">1993</lido:displayDate>
                  <lido:displayDate xml:lang="ko">1993년</lido:displayDate>
                  <lido:displayDate xml:lang="pl">1993</lido:displayDate>
                  <lido:displayDate xml:lang="pt">1993</lido:displayDate>
                  <lido:displayDate xml:lang="ro">1993</lido:displayDate>
                  <lido:displayDate xml:lang="ru">1993</lido:displayDate>
                  <lido:displayDate xml:lang="ta">1993</lido:displayDate>
                  <lido:displayDate xml:lang="tl">1993</lido:displayDate>
                  <lido:displayDate xml:lang="tr">1993</lido:displayDate>
                  <lido:displayDate xml:lang="zh">1993年</lido:displayDate>
                  <lido:date>
                     <lido:earliestDate>1993</lido:earliestDate>
                     <lido:latestDate>1993</lido:latestDate>
                  </lido:date>
               </lido:eventDate>
               <lido:eventPlace>
                  <lido:displayPlace>Berlin</lido:displayPlace>
                  <lido:displayPlace xml:lang="ar">برلين</lido:displayPlace>
                  <lido:displayPlace xml:lang="bn">বার্লিন</lido:displayPlace>
                  <lido:displayPlace xml:lang="cs">Berlín</lido:displayPlace>
                  <lido:displayPlace xml:lang="da">Berlin</lido:displayPlace>
                  <lido:displayPlace xml:lang="el">Βερολίνο</lido:displayPlace>
                  <lido:displayPlace xml:lang="en">Berlin</lido:displayPlace>
                  <lido:displayPlace xml:lang="es">Berlín</lido:displayPlace>
                  <lido:displayPlace xml:lang="fa">برلین</lido:displayPlace>
                  <lido:displayPlace xml:lang="fi">Berliini</lido:displayPlace>
                  <lido:displayPlace xml:lang="fr">Berlin</lido:displayPlace>
                  <lido:displayPlace xml:lang="ha">Berlin</lido:displayPlace>
                  <lido:displayPlace xml:lang="he">ברלין</lido:displayPlace>
                  <lido:displayPlace xml:lang="hi">बर्लिन</lido:displayPlace>
                  <lido:displayPlace xml:lang="hu">Berlin</lido:displayPlace>
                  <lido:displayPlace xml:lang="id">Berlin</lido:displayPlace>
                  <lido:displayPlace xml:lang="it">Berlino</lido:displayPlace>
                  <lido:displayPlace xml:lang="ja">ベルリン</lido:displayPlace>
                  <lido:displayPlace xml:lang="ka">ბერლინი</lido:displayPlace>
                  <lido:displayPlace xml:lang="ko">베를린</lido:displayPlace>
                  <lido:displayPlace xml:lang="nl">Berlijn</lido:displayPlace>
                  <lido:displayPlace xml:lang="pl">Berlin</lido:displayPlace>
                  <lido:displayPlace xml:lang="pt">Berlim</lido:displayPlace>
                  <lido:displayPlace xml:lang="ro">Berlin</lido:displayPlace>
                  <lido:displayPlace xml:lang="ru">Берлин</lido:displayPlace>
                  <lido:displayPlace xml:lang="sv">Berlin</lido:displayPlace>
                  <lido:displayPlace xml:lang="sw">Berlin</lido:displayPlace>
                  <lido:displayPlace xml:lang="ta">பெர்லின்</lido:displayPlace>
                  <lido:displayPlace xml:lang="th">เบอร์ลิน</lido:displayPlace>
                  <lido:displayPlace xml:lang="tl">Berlin</lido:displayPlace>
                  <lido:displayPlace xml:lang="tr">Berlin</lido:displayPlace>
                  <lido:displayPlace xml:lang="ur">برلن</lido:displayPlace>
                  <lido:displayPlace xml:lang="vi">Berlin</lido:displayPlace>
                  <lido:displayPlace xml:lang="zh">柏林</lido:displayPlace>
                  <lido:place>
                     <lido:placeID lido:source="geonames" lido:type="uri">https://sws.geonames.org/2950159</lido:placeID>
                     <lido:placeID lido:source="TGN" lido:type="uri">http://vocab.getty.edu/tgn/7209904</lido:placeID>
                     <lido:placeID lido:source="gnd" lido:type="uri">https://d-nb.info/gnd/4005728-8</lido:placeID>
                     <lido:placeID lido:source="wikidata" lido:type="uri">https://www.wikidata.org/wiki/Q64</lido:placeID>
                     <lido:placeID lido:source="md:term" lido:type="uri">https://term.museum-digital.de/md-de/place/61</lido:placeID>
                     <lido:namePlaceSet>
                        <lido:appellationValue>Berlin</lido:appellationValue>
                        <lido:appellationValue xml:lang="ar">برلين</lido:appellationValue>
                        <lido:appellationValue xml:lang="bn">বার্লিন</lido:appellationValue>
                        <lido:appellationValue xml:lang="cs">Berlín</lido:appellationValue>
                        <lido:appellationValue xml:lang="da">Berlin</lido:appellationValue>
                        <lido:appellationValue xml:lang="el">Βερολίνο</lido:appellationValue>
                        <lido:appellationValue xml:lang="en">Berlin</lido:appellationValue>
                        <lido:appellationValue xml:lang="es">Berlín</lido:appellationValue>
                        <lido:appellationValue xml:lang="fa">برلین</lido:appellationValue>
                        <lido:appellationValue xml:lang="fi">Berliini</lido:appellationValue>
                        <lido:appellationValue xml:lang="fr">Berlin</lido:appellationValue>
                        <lido:appellationValue xml:lang="ha">Berlin</lido:appellationValue>
                        <lido:appellationValue xml:lang="he">ברלין</lido:appellationValue>
                        <lido:appellationValue xml:lang="hi">बर्लिन</lido:appellationValue>
                        <lido:appellationValue xml:lang="hu">Berlin</lido:appellationValue>
                        <lido:appellationValue xml:lang="id">Berlin</lido:appellationValue>
                        <lido:appellationValue xml:lang="it">Berlino</lido:appellationValue>
                        <lido:appellationValue xml:lang="ja">ベルリン</lido:appellationValue>
                        <lido:appellationValue xml:lang="ka">ბერლინი</lido:appellationValue>
                        <lido:appellationValue xml:lang="ko">베를린</lido:appellationValue>
                        <lido:appellationValue xml:lang="nl">Berlijn</lido:appellationValue>
                        <lido:appellationValue xml:lang="pl">Berlin</lido:appellationValue>
                        <lido:appellationValue xml:lang="pt">Berlim</lido:appellationValue>
                        <lido:appellationValue xml:lang="ro">Berlin</lido:appellationValue>
                        <lido:appellationValue xml:lang="ru">Берлин</lido:appellationValue>
                        <lido:appellationValue xml:lang="sv">Berlin</lido:appellationValue>
                        <lido:appellationValue xml:lang="sw">Berlin</lido:appellationValue>
                        <lido:appellationValue xml:lang="ta">பெர்லின்</lido:appellationValue>
                        <lido:appellationValue xml:lang="th">เบอร์ลิน</lido:appellationValue>
                        <lido:appellationValue xml:lang="tl">Berlin</lido:appellationValue>
                        <lido:appellationValue xml:lang="tr">Berlin</lido:appellationValue>
                        <lido:appellationValue xml:lang="ur">برلن</lido:appellationValue>
                        <lido:appellationValue xml:lang="vi">Berlin</lido:appellationValue>
                        <lido:appellationValue xml:lang="zh">柏林</lido:appellationValue>
                     </lido:namePlaceSet>
                     <lido:gml>
                        <gml:Point srsName="EPSG:4326">
                           <gml:pos>52.516666412354 13.383333206177</gml:pos>
                        </gml:Point>
                     </lido:gml>
                  </lido:place>
               </lido:eventPlace>
            </lido:event>
         </lido:eventSet>
         <lido:eventSet>
            <lido:displayEvent>Verkauft</lido:displayEvent>
            <lido:event>
               <lido:eventType>
                  <lido:conceptID lido:type="uri">http://terminology.lido-schema.org/lido00005</lido:conceptID>
                  <lido:term lido:addedSearchTerm="no">Verkauft</lido:term>
               </lido:eventType>
               <lido:eventActor>
                  <lido:displayActorInRole>Jörg Hein</lido:displayActorInRole>
                  <lido:actorInRole>
                     <lido:actor>
                        <lido:actorID lido:source="md:term" lido:type="uri">https://term.museum-digital.de/md-de/persinst/152350</lido:actorID>
                        <lido:nameActorSet>
                           <lido:appellationValue>Hein, Jörg</lido:appellationValue>
                        </lido:nameActorSet>
                     </lido:actor>
                  </lido:actorInRole>
               </lido:eventActor>
               <lido:eventDate>
                  <lido:displayDate>1995</lido:displayDate>
                  <lido:displayDate xml:lang="ar">1995</lido:displayDate>
                  <lido:displayDate xml:lang="en">1995</lido:displayDate>
                  <lido:displayDate xml:lang="es">1995</lido:displayDate>
                  <lido:displayDate xml:lang="fa">1995</lido:displayDate>
                  <lido:displayDate xml:lang="fr">1995</lido:displayDate>
                  <lido:displayDate xml:lang="hu">1995</lido:displayDate>
                  <lido:displayDate xml:lang="id">1995</lido:displayDate>
                  <lido:displayDate xml:lang="it">1995</lido:displayDate>
                  <lido:displayDate xml:lang="ja">1995年</lido:displayDate>
                  <lido:displayDate xml:lang="ka">1995</lido:displayDate>
                  <lido:displayDate xml:lang="ko">1995년</lido:displayDate>
                  <lido:displayDate xml:lang="pl">1995</lido:displayDate>
                  <lido:displayDate xml:lang="pt">1995</lido:displayDate>
                  <lido:displayDate xml:lang="ro">1995</lido:displayDate>
                  <lido:displayDate xml:lang="ru">1995</lido:displayDate>
                  <lido:displayDate xml:lang="ta">1995</lido:displayDate>
                  <lido:displayDate xml:lang="tl">1995</lido:displayDate>
                  <lido:displayDate xml:lang="tr">1995</lido:displayDate>
                  <lido:displayDate xml:lang="zh">1995年</lido:displayDate>
                  <lido:date>
                     <lido:earliestDate>1995</lido:earliestDate>
                     <lido:latestDate>1995</lido:latestDate>
                  </lido:date>
               </lido:eventDate>
               <lido:eventPlace>
                  <lido:displayPlace>Berlin</lido:displayPlace>
                  <lido:displayPlace xml:lang="ar">برلين</lido:displayPlace>
                  <lido:displayPlace xml:lang="bn">বার্লিন</lido:displayPlace>
                  <lido:displayPlace xml:lang="cs">Berlín</lido:displayPlace>
                  <lido:displayPlace xml:lang="da">Berlin</lido:displayPlace>
                  <lido:displayPlace xml:lang="el">Βερολίνο</lido:displayPlace>
                  <lido:displayPlace xml:lang="en">Berlin</lido:displayPlace>
                  <lido:displayPlace xml:lang="es">Berlín</lido:displayPlace>
                  <lido:displayPlace xml:lang="fa">برلین</lido:displayPlace>
                  <lido:displayPlace xml:lang="fi">Berliini</lido:displayPlace>
                  <lido:displayPlace xml:lang="fr">Berlin</lido:displayPlace>
                  <lido:displayPlace xml:lang="ha">Berlin</lido:displayPlace>
                  <lido:displayPlace xml:lang="he">ברלין</lido:displayPlace>
                  <lido:displayPlace xml:lang="hi">बर्लिन</lido:displayPlace>
                  <lido:displayPlace xml:lang="hu">Berlin</lido:displayPlace>
                  <lido:displayPlace xml:lang="id">Berlin</lido:displayPlace>
                  <lido:displayPlace xml:lang="it">Berlino</lido:displayPlace>
                  <lido:displayPlace xml:lang="ja">ベルリン</lido:displayPlace>
                  <lido:displayPlace xml:lang="ka">ბერლინი</lido:displayPlace>
                  <lido:displayPlace xml:lang="ko">베를린</lido:displayPlace>
                  <lido:displayPlace xml:lang="nl">Berlijn</lido:displayPlace>
                  <lido:displayPlace xml:lang="pl">Berlin</lido:displayPlace>
                  <lido:displayPlace xml:lang="pt">Berlim</lido:displayPlace>
                  <lido:displayPlace xml:lang="ro">Berlin</lido:displayPlace>
                  <lido:displayPlace xml:lang="ru">Берлин</lido:displayPlace>
                  <lido:displayPlace xml:lang="sv">Berlin</lido:displayPlace>
                  <lido:displayPlace xml:lang="sw">Berlin</lido:displayPlace>
                  <lido:displayPlace xml:lang="ta">பெர்லின்</lido:displayPlace>
                  <lido:displayPlace xml:lang="th">เบอร์ลิน</lido:displayPlace>
                  <lido:displayPlace xml:lang="tl">Berlin</lido:displayPlace>
                  <lido:displayPlace xml:lang="tr">Berlin</lido:displayPlace>
                  <lido:displayPlace xml:lang="ur">برلن</lido:displayPlace>
                  <lido:displayPlace xml:lang="vi">Berlin</lido:displayPlace>
                  <lido:displayPlace xml:lang="zh">柏林</lido:displayPlace>
                  <lido:place>
                     <lido:placeID lido:source="geonames" lido:type="uri">https://sws.geonames.org/2950159</lido:placeID>
                     <lido:placeID lido:source="TGN" lido:type="uri">http://vocab.getty.edu/tgn/7209904</lido:placeID>
                     <lido:placeID lido:source="gnd" lido:type="uri">https://d-nb.info/gnd/4005728-8</lido:placeID>
                     <lido:placeID lido:source="wikidata" lido:type="uri">https://www.wikidata.org/wiki/Q64</lido:placeID>
                     <lido:placeID lido:source="md:term" lido:type="uri">https://term.museum-digital.de/md-de/place/61</lido:placeID>
                     <lido:namePlaceSet>
                        <lido:appellationValue>Berlin</lido:appellationValue>
                        <lido:appellationValue xml:lang="ar">برلين</lido:appellationValue>
                        <lido:appellationValue xml:lang="bn">বার্লিন</lido:appellationValue>
                        <lido:appellationValue xml:lang="cs">Berlín</lido:appellationValue>
                        <lido:appellationValue xml:lang="da">Berlin</lido:appellationValue>
                        <lido:appellationValue xml:lang="el">Βερολίνο</lido:appellationValue>
                        <lido:appellationValue xml:lang="en">Berlin</lido:appellationValue>
                        <lido:appellationValue xml:lang="es">Berlín</lido:appellationValue>
                        <lido:appellationValue xml:lang="fa">برلین</lido:appellationValue>
                        <lido:appellationValue xml:lang="fi">Berliini</lido:appellationValue>
                        <lido:appellationValue xml:lang="fr">Berlin</lido:appellationValue>
                        <lido:appellationValue xml:lang="ha">Berlin</lido:appellationValue>
                        <lido:appellationValue xml:lang="he">ברלין</lido:appellationValue>
                        <lido:appellationValue xml:lang="hi">बर्लिन</lido:appellationValue>
                        <lido:appellationValue xml:lang="hu">Berlin</lido:appellationValue>
                        <lido:appellationValue xml:lang="id">Berlin</lido:appellationValue>
                        <lido:appellationValue xml:lang="it">Berlino</lido:appellationValue>
                        <lido:appellationValue xml:lang="ja">ベルリン</lido:appellationValue>
                        <lido:appellationValue xml:lang="ka">ბერლინი</lido:appellationValue>
                        <lido:appellationValue xml:lang="ko">베를린</lido:appellationValue>
                        <lido:appellationValue xml:lang="nl">Berlijn</lido:appellationValue>
                        <lido:appellationValue xml:lang="pl">Berlin</lido:appellationValue>
                        <lido:appellationValue xml:lang="pt">Berlim</lido:appellationValue>
                        <lido:appellationValue xml:lang="ro">Berlin</lido:appellationValue>
                        <lido:appellationValue xml:lang="ru">Берлин</lido:appellationValue>
                        <lido:appellationValue xml:lang="sv">Berlin</lido:appellationValue>
                        <lido:appellationValue xml:lang="sw">Berlin</lido:appellationValue>
                        <lido:appellationValue xml:lang="ta">பெர்லின்</lido:appellationValue>
                        <lido:appellationValue xml:lang="th">เบอร์ลิน</lido:appellationValue>
                        <lido:appellationValue xml:lang="tl">Berlin</lido:appellationValue>
                        <lido:appellationValue xml:lang="tr">Berlin</lido:appellationValue>
                        <lido:appellationValue xml:lang="ur">برلن</lido:appellationValue>
                        <lido:appellationValue xml:lang="vi">Berlin</lido:appellationValue>
                        <lido:appellationValue xml:lang="zh">柏林</lido:appellationValue>
                     </lido:namePlaceSet>
                     <lido:gml>
                        <gml:Point srsName="EPSG:4326">
                           <gml:pos>52.516666412354 13.383333206177</gml:pos>
                        </gml:Point>
                     </lido:gml>
                  </lido:place>
               </lido:eventPlace>
            </lido:event>
         </lido:eventSet>
      </lido:eventWrap>
      <lido:objectRelationWrap>
         <lido:subjectWrap>
            <lido:subjectSet>
               <lido:subject>
                  <lido:subjectConcept>
                     <lido:conceptID lido:source="Wikipedia" lido:type="uri">https://de.wikipedia.org/wiki/Uhr</lido:conceptID>
                     <lido:conceptID lido:source="gnd" lido:type="uri">https://d-nb.info/gnd/4164176-0</lido:conceptID>
                     <lido:conceptID lido:source="lcsh" lido:type="uri">http://id.loc.gov/authorities/subjects/sh85027100</lido:conceptID>
                     <lido:conceptID lido:source="aat" lido:type="uri">http://vocab.getty.edu/aat/300041575</lido:conceptID>
                     <lido:conceptID lido:source="grobsystematik" lido:type="uri">https://term.museum-digital.de/grobsystematik/tag/13321</lido:conceptID>
                     <lido:conceptID lido:source="oberbegriffsdatei" lido:type="uri">https://term.museum-digital.de/Oberbegriffsdatei/tag/2036</lido:conceptID>
                     <lido:conceptID lido:source="wikidata" lido:type="uri">https://www.wikidata.org/wiki/Q376</lido:conceptID>
                     <lido:conceptID lido:source="md:term" lido:type="uri">https://term.museum-digital.de/md-de/tag/1331</lido:conceptID>
                     <lido:term lido:addedSearchTerm="no">Uhr</lido:term>
                     <lido:term lido:addedSearchTerm="no" xml:lang="ar">ساعة</lido:term>
                     <lido:term lido:addedSearchTerm="no" xml:lang="bn">ঘড়ি</lido:term>
                     <lido:term lido:addedSearchTerm="no" xml:lang="cs">Hodiny</lido:term>
                     <lido:term lido:addedSearchTerm="no" xml:lang="da">Ur</lido:term>
                     <lido:term lido:addedSearchTerm="no" xml:lang="el">Ρολόι</lido:term>
                     <lido:term lido:addedSearchTerm="no" xml:lang="en">Clock</lido:term>
                     <lido:term lido:addedSearchTerm="no" xml:lang="es">Reloj</lido:term>
                     <lido:term lido:addedSearchTerm="no" xml:lang="fa">ساعت</lido:term>
                     <lido:term lido:addedSearchTerm="no" xml:lang="fi">Kello</lido:term>
                     <lido:term lido:addedSearchTerm="no" xml:lang="fr">Horloge</lido:term>
                     <lido:term lido:addedSearchTerm="no" xml:lang="ha">agogo</lido:term>
                     <lido:term lido:addedSearchTerm="no" xml:lang="he">שעון</lido:term>
                     <lido:term lido:addedSearchTerm="no" xml:lang="hi">घडी</lido:term>
                     <lido:term lido:addedSearchTerm="no" xml:lang="hu">óra</lido:term>
                     <lido:term lido:addedSearchTerm="no" xml:lang="id">Jam</lido:term>
                     <lido:term lido:addedSearchTerm="no" xml:lang="it">Orologio</lido:term>
                     <lido:term lido:addedSearchTerm="no" xml:lang="ja">時計</lido:term>
                     <lido:term lido:addedSearchTerm="no" xml:lang="ka">საათი</lido:term>
                     <lido:term lido:addedSearchTerm="no" xml:lang="ko">시계</lido:term>
                     <lido:term lido:addedSearchTerm="no" xml:lang="nl">Klok</lido:term>
                     <lido:term lido:addedSearchTerm="no" xml:lang="pl">Zegar</lido:term>
                     <lido:term lido:addedSearchTerm="no" xml:lang="pt">Relógio</lido:term>
                     <lido:term lido:addedSearchTerm="no" xml:lang="ro">ceas</lido:term>
                     <lido:term lido:addedSearchTerm="no" xml:lang="ru">часы</lido:term>
                     <lido:term lido:addedSearchTerm="no" xml:lang="sv">Klocka</lido:term>
                     <lido:term lido:addedSearchTerm="no" xml:lang="sw">saa</lido:term>
                     <lido:term lido:addedSearchTerm="no" xml:lang="ta">கடிகாரம்</lido:term>
                     <lido:term lido:addedSearchTerm="no" xml:lang="th">นาฬิกา</lido:term>
                     <lido:term lido:addedSearchTerm="no" xml:lang="tl">Orasan</lido:term>
                     <lido:term lido:addedSearchTerm="no" xml:lang="tr">Saat</lido:term>
                     <lido:term lido:addedSearchTerm="no" xml:lang="ur">گھنٹا</lido:term>
                     <lido:term lido:addedSearchTerm="no" xml:lang="vi">Đồng hồ</lido:term>
                     <lido:term lido:addedSearchTerm="no" xml:lang="zh">時鐘</lido:term>
                  </lido:subjectConcept>
               </lido:subject>
            </lido:subjectSet>
            <lido:subjectSet>
               <lido:subject>
                  <lido:subjectConcept>
                     <lido:conceptID lido:source="gnd" lido:type="uri">http://d-nb.info/gnd/4127004-6</lido:conceptID>
                     <lido:conceptID lido:source="grobsystematik" lido:type="uri">https://term.museum-digital.de/grobsystematik/tag/12840</lido:conceptID>
                     <lido:conceptID lido:source="md:term" lido:type="uri">https://term.museum-digital.de/md-de/tag/10272</lido:conceptID>
                     <lido:term lido:addedSearchTerm="no">Tischuhr</lido:term>
                     <lido:term lido:addedSearchTerm="no" xml:lang="en">Table clock</lido:term>
                  </lido:subjectConcept>
               </lido:subject>
            </lido:subjectSet>
            <lido:subjectSet>
               <lido:subject>
                  <lido:subjectConcept>
                     <lido:conceptID lido:source="gnd" lido:type="uri">https://d-nb.info/gnd/4121901-6</lido:conceptID>
                     <lido:conceptID lido:source="grobsystematik" lido:type="uri">https://term.museum-digital.de/grobsystematik/tag/13917</lido:conceptID>
                     <lido:conceptID lido:source="oberbegriffsdatei" lido:type="uri">https://term.museum-digital.de/oberbegriffsdatei/tag/4377</lido:conceptID>
                     <lido:conceptID lido:source="Wikipedia" lido:type="uri">https://de.wikipedia.org/wiki/Wanduhr</lido:conceptID>
                     <lido:conceptID lido:source="aat" lido:type="uri">https://vocab.getty.edu/page/aat/300041592</lido:conceptID>
                     <lido:conceptID lido:source="wikidata" lido:type="uri">https://www.wikidata.org/wiki/Q31843230</lido:conceptID>
                     <lido:conceptID lido:source="md:term" lido:type="uri">https://term.museum-digital.de/md-de/tag/12970</lido:conceptID>
                     <lido:term lido:addedSearchTerm="no">Wanduhr</lido:term>
                     <lido:term lido:addedSearchTerm="no" xml:lang="en">Wall clock</lido:term>
                     <lido:term lido:addedSearchTerm="no" xml:lang="fr">Horloge murale</lido:term>
                     <lido:term lido:addedSearchTerm="no" xml:lang="sv">Väggur</lido:term>
                  </lido:subjectConcept>
               </lido:subject>
            </lido:subjectSet>
            <lido:subjectSet>
               <lido:subject>
                  <lido:subjectConcept>
                     <lido:conceptID lido:source="md:term" lido:type="uri">https://term.museum-digital.de/md-de/tag/89495</lido:conceptID>
                     <lido:term lido:addedSearchTerm="no">Konsoluhr</lido:term>
                  </lido:subjectConcept>
               </lido:subject>
            </lido:subjectSet>
         </lido:subjectWrap>
         <lido:relatedWorksWrap>
            <lido:relatedWorkSet>
               <lido:relatedWork>
                  <lido:displayObject>Stiftung Stadtmuseum Berlin, Inv. Nr. 98/2 UH&lt;br&gt;
Stiftung Stadtmuseum Berlin, Inv. Nr. 98/233 UH&lt;br&gt;
Stiftung Stadtmuseum Berlin, Inv. Nr. KH 2001/16 UH</lido:displayObject>
               </lido:relatedWork>
            </lido:relatedWorkSet>
            <lido:relatedWorkSet>
               <lido:relatedWork>
                  <lido:displayObject>Mikrolisk. The horological trade mark list.</lido:displayObject>
                  <lido:object>
                     <lido:objectWebResource>http://www.mikrolisk.de/show.php?site=280&amp;suchwort=Marti&amp;searchWhere=all#sucheMarker</lido:objectWebResource>
                  </lido:object>
               </lido:relatedWork>
            </lido:relatedWorkSet>
            <lido:relatedWorkSet>
               <lido:relatedWork>
                  <lido:displayObject>Abeler, Jürgen, 2010: Meister der Uhrmacherkunst, Wuppertal, S. 259, 452, 575</lido:displayObject>
               </lido:relatedWork>
            </lido:relatedWorkSet>
            <lido:relatedWorkSet>
               <lido:relatedWork>
                  <lido:displayObject>Mühe, Richard; Vogel, Horand M., 1997: Faszination Uhren. Europäische Tischuhren, Wanduhren, Bodenstanduhren. Eine Standardwerk, Hamburg, S. 98, 99</lido:displayObject>
               </lido:relatedWork>
            </lido:relatedWorkSet>
            <lido:relatedWorkSet>
               <lido:relatedWork>
                  <lido:displayObject>Lehner, Sigmund, 1909: Die Imitationen. Eine Anleitung zur Nachahmung von Natur- und Kunstprodukten wie: Elfenbein, Schildblatt, Perlen und Perlmutter, Korallen, Bernstein, Horn, Hirschhorn, Fischbein, Alabaster, Marmor, Malachit, Avanturin, Lapislazuli, Onyx, Meerschaum, Schiefer, edlen Hölzern, sowie zur Anfertiguung von Kunst-Steinmassen, Nachbildungen von Holzschnitzereien, Bildhauer-Arbeiten, Mosaiken, Intarsien, Leder, Seide usw. 3. bed. erw. Aufl. (= A. Hartlebens chemisch-technische Bibliothek; 101), Wien, Leipzig, S. 89</lido:displayObject>
               </lido:relatedWork>
            </lido:relatedWorkSet>
            <lido:relatedWorkSet>
               <lido:relatedWork>
                  <lido:displayObject>Lengellé, Henri-Gustave, 1971–1972: Dictionnaire des horlogers français. Documentation réuni par Tardy, avec l'apport des travaux de Paul Brateau ... et de Robert Ardignac. 2 Bde, Paris, S. 325, 326</lido:displayObject>
               </lido:relatedWork>
            </lido:relatedWorkSet>
         </lido:relatedWorksWrap>
      </lido:objectRelationWrap>
   </lido:descriptiveMetadata>
   <lido:administrativeMetadata xml:lang="de">
      <lido:rightsWorkWrap>
         <lido:rightsWorkSet>
            <lido:rightsHolder>
               <lido:legalBodyName>
                  <lido:appellationValue>Stiftung Stadtmuseum Berlin</lido:appellationValue>
               </lido:legalBodyName>
            </lido:rightsHolder>
         </lido:rightsWorkSet>
      </lido:rightsWorkWrap>
      <lido:recordWrap>
         <lido:recordID lido:type="museum-digital">86350</lido:recordID>
         <lido:recordType>
            <lido:term lido:addedSearchTerm="no">item</lido:term>
         </lido:recordType>
         <lido:recordSource lido:type="dataProvider">
            <lido:legalBodyName>
               <lido:appellationValue>museum-digital</lido:appellationValue>
            </lido:legalBodyName>
            <lido:legalBodyWeblink>https://berlin.museum-digital.de/</lido:legalBodyWeblink>
         </lido:recordSource>
         <lido:recordSource>
            <lido:legalBodyID lido:type="isil">DE-MUS-061525</lido:legalBodyID>
            <lido:legalBodyName>
               <lido:appellationValue>Stiftung Stadtmuseum Berlin</lido:appellationValue>
            </lido:legalBodyName>
         </lido:recordSource>
         <lido:recordRights>
            <lido:rightsType>
               <lido:conceptID lido:type="uri">https://creativecommons.org/publicdomain/zero/1.0/</lido:conceptID>
               <lido:term lido:addedSearchTerm="no">CC 0</lido:term>
            </lido:rightsType>
            <lido:rightsHolder>
               <lido:legalBodyID lido:type="isil">DE-MUS-061525</lido:legalBodyID>
               <lido:legalBodyName>
                  <lido:appellationValue>Stiftung Stadtmuseum Berlin</lido:appellationValue>
               </lido:legalBodyName>
               <lido:legalBodyWeblink>https://www.stadtmuseum.de</lido:legalBodyWeblink>
            </lido:rightsHolder>
            <lido:creditLine>Förderprogramm zur Digitalisierung von Objekten des kulturellen Erbes des Landes Berlin</lido:creditLine>
         </lido:recordRights>
         <lido:recordInfoSet>
            <lido:recordInfoLink>https://berlin.museum-digital.de/index.php?t=objekt&amp;oges=86350</lido:recordInfoLink>
            <lido:recordMetadataDate>2021-02-23 13:46:54</lido:recordMetadataDate>
         </lido:recordInfoSet>
      </lido:recordWrap>
      <lido:resourceWrap>
         <lido:resourceSet lido:sortorder="1">
            <lido:resourceID lido:source="image" lido:type="local">59867</lido:resourceID>
            <lido:resourceRepresentation lido:type="image_thumb">
               <lido:linkResource lido:formatResource="image/jpeg">https://berlin.museum-digital.de/data/berlin/images/21/86350-ii_9526_i/johannes_hartmann_konsolu/100h_johannes-hartmann-konsoluhr-spaetes-19-jahrhundert-inv-nr-ii-9526-i-86350-3.jpg</lido:linkResource>
            </lido:resourceRepresentation>
            <lido:resourceRepresentation lido:type="image_preview">
               <lido:linkResource lido:formatResource="image/jpeg">https://berlin.museum-digital.de/data/berlin/images/21/86350-ii_9526_i/johannes_hartmann_konsolu/200w_johannes-hartmann-konsoluhr-spaetes-19-jahrhundert-inv-nr-ii-9526-i-86350-3.jpg</lido:linkResource>
            </lido:resourceRepresentation>
            <lido:resourceRepresentation lido:type="http://terminology.lido-schema.org/lido00464">
               <lido:linkResource lido:formatResource="image/jpeg">https://berlin.museum-digital.de/data/berlin/images/21/86350-ii_9526_i/johannes_hartmann_konsolu/johannes-hartmann-konsoluhr-spaetes-19-jahrhundert-inv-nr-ii-9526-i-86350-3.jpg</lido:linkResource>
            </lido:resourceRepresentation>
            <lido:resourceType>
               <lido:term>image</lido:term>
            </lido:resourceType>
            <lido:resourceSource lido:type="creator">
               <lido:legalBodyName>
                  <lido:appellationValue>Oliver Ziebe, Berlin (2020)</lido:appellationValue>
               </lido:legalBodyName>
            </lido:resourceSource>
            <lido:rightsResource>
               <lido:rightsType>
                  <lido:conceptID lido:type="uri">https://creativecommons.org/licenses/by/4.0/</lido:conceptID>
                  <lido:term>CC BY 4.0</lido:term>
               </lido:rightsType>
               <lido:rightsHolder>
                  <lido:legalBodyName>
                     <lido:appellationValue>Stiftung Stadtmuseum Berlin</lido:appellationValue>
                  </lido:legalBodyName>
               </lido:rightsHolder>
            </lido:rightsResource>
         </lido:resourceSet>
         <lido:resourceSet lido:sortorder="2">
            <lido:resourceID lido:source="image" lido:type="local">59866</lido:resourceID>
            <lido:resourceRepresentation lido:type="image_thumb">
               <lido:linkResource lido:formatResource="image/jpeg">https://berlin.museum-digital.de/data/berlin/images/21/86350-ii_9526_i/johannes_hartmann_konsolu/100h_johannes-hartmann-konsoluhr-spaetes-19-jahrhundert-inv-nr-ii-9526-i-86350-2.jpg</lido:linkResource>
            </lido:resourceRepresentation>
            <lido:resourceRepresentation lido:type="image_preview">
               <lido:linkResource lido:formatResource="image/jpeg">https://berlin.museum-digital.de/data/berlin/images/21/86350-ii_9526_i/johannes_hartmann_konsolu/200w_johannes-hartmann-konsoluhr-spaetes-19-jahrhundert-inv-nr-ii-9526-i-86350-2.jpg</lido:linkResource>
            </lido:resourceRepresentation>
            <lido:resourceRepresentation lido:type="http://terminology.lido-schema.org/lido00464">
               <lido:linkResource lido:formatResource="image/jpeg">https://berlin.museum-digital.de/data/berlin/images/21/86350-ii_9526_i/johannes_hartmann_konsolu/johannes-hartmann-konsoluhr-spaetes-19-jahrhundert-inv-nr-ii-9526-i-86350-2.jpg</lido:linkResource>
            </lido:resourceRepresentation>
            <lido:resourceType>
               <lido:term>image</lido:term>
            </lido:resourceType>
            <lido:resourceRelType>
               <lido:term>Hauptansicht</lido:term>
            </lido:resourceRelType>
            <lido:resourceSource lido:type="creator">
               <lido:legalBodyName>
                  <lido:appellationValue>Oliver Ziebe, Berlin (2020)</lido:appellationValue>
               </lido:legalBodyName>
            </lido:resourceSource>
            <lido:rightsResource>
               <lido:rightsType>
                  <lido:conceptID lido:type="uri">https://creativecommons.org/licenses/by/4.0/</lido:conceptID>
                  <lido:term>CC BY 4.0</lido:term>
               </lido:rightsType>
               <lido:rightsHolder>
                  <lido:legalBodyName>
                     <lido:appellationValue>Stiftung Stadtmuseum Berlin</lido:appellationValue>
                  </lido:legalBodyName>
               </lido:rightsHolder>
            </lido:rightsResource>
         </lido:resourceSet>
         <lido:resourceSet lido:sortorder="3">
            <lido:resourceID lido:source="image" lido:type="local">59865</lido:resourceID>
            <lido:resourceRepresentation lido:type="image_thumb">
               <lido:linkResource lido:formatResource="image/jpeg">https://berlin.museum-digital.de/data/berlin/images/21/86350-ii_9526_i/johannes_hartmann_konsolu/100h_johannes-hartmann-konsoluhr-spaetes-19-jahrhundert-inv-nr-ii-9526-i-86350.jpg</lido:linkResource>
            </lido:resourceRepresentation>
            <lido:resourceRepresentation lido:type="image_preview">
               <lido:linkResource lido:formatResource="image/jpeg">https://berlin.museum-digital.de/data/berlin/images/21/86350-ii_9526_i/johannes_hartmann_konsolu/200w_johannes-hartmann-konsoluhr-spaetes-19-jahrhundert-inv-nr-ii-9526-i-86350.jpg</lido:linkResource>
            </lido:resourceRepresentation>
            <lido:resourceRepresentation lido:type="http://terminology.lido-schema.org/lido00464">
               <lido:linkResource lido:formatResource="image/jpeg">https://berlin.museum-digital.de/data/berlin/images/21/86350-ii_9526_i/johannes_hartmann_konsolu/johannes-hartmann-konsoluhr-spaetes-19-jahrhundert-inv-nr-ii-9526-i-86350.jpg</lido:linkResource>
            </lido:resourceRepresentation>
            <lido:resourceType>
               <lido:term>image</lido:term>
            </lido:resourceType>
            <lido:resourceSource lido:type="creator">
               <lido:legalBodyName>
                  <lido:appellationValue>Oliver Ziebe, Berlin (2020)</lido:appellationValue>
               </lido:legalBodyName>
            </lido:resourceSource>
            <lido:rightsResource>
               <lido:rightsType>
                  <lido:conceptID lido:type="uri">https://creativecommons.org/licenses/by/4.0/</lido:conceptID>
                  <lido:term>CC BY 4.0</lido:term>
               </lido:rightsType>
               <lido:rightsHolder>
                  <lido:legalBodyName>
                     <lido:appellationValue>Stiftung Stadtmuseum Berlin</lido:appellationValue>
                  </lido:legalBodyName>
               </lido:rightsHolder>
            </lido:rightsResource>
         </lido:resourceSet>
         <lido:resourceSet lido:sortorder="4">
            <lido:resourceID lido:source="image" lido:type="local">59868</lido:resourceID>
            <lido:resourceRepresentation lido:type="image_thumb">
               <lido:linkResource lido:formatResource="image/jpeg">https://berlin.museum-digital.de/data/berlin/images/21/86350-ii_9526_i/johannes_hartmann_konsolu/100h_johannes-hartmann-konsoluhr-spaetes-19-jahrhundert-inv-nr-ii-9526-i-86350-4.jpg</lido:linkResource>
            </lido:resourceRepresentation>
            <lido:resourceRepresentation lido:type="image_preview">
               <lido:linkResource lido:formatResource="image/jpeg">https://berlin.museum-digital.de/data/berlin/images/21/86350-ii_9526_i/johannes_hartmann_konsolu/200w_johannes-hartmann-konsoluhr-spaetes-19-jahrhundert-inv-nr-ii-9526-i-86350-4.jpg</lido:linkResource>
            </lido:resourceRepresentation>
            <lido:resourceRepresentation lido:type="http://terminology.lido-schema.org/lido00464">
               <lido:linkResource lido:formatResource="image/jpeg">https://berlin.museum-digital.de/data/berlin/images/21/86350-ii_9526_i/johannes_hartmann_konsolu/johannes-hartmann-konsoluhr-spaetes-19-jahrhundert-inv-nr-ii-9526-i-86350-4.jpg</lido:linkResource>
            </lido:resourceRepresentation>
            <lido:resourceType>
               <lido:term>image</lido:term>
            </lido:resourceType>
            <lido:resourceSource lido:type="creator">
               <lido:legalBodyName>
                  <lido:appellationValue>Oliver Ziebe, Berlin (2020)</lido:appellationValue>
               </lido:legalBodyName>
            </lido:resourceSource>
            <lido:rightsResource>
               <lido:rightsType>
                  <lido:conceptID lido:type="uri">https://creativecommons.org/licenses/by/4.0/</lido:conceptID>
                  <lido:term>CC BY 4.0</lido:term>
               </lido:rightsType>
               <lido:rightsHolder>
                  <lido:legalBodyName>
                     <lido:appellationValue>Stiftung Stadtmuseum Berlin</lido:appellationValue>
                  </lido:legalBodyName>
               </lido:rightsHolder>
            </lido:rightsResource>
         </lido:resourceSet>
         <lido:resourceSet lido:sortorder="5">
            <lido:resourceID lido:source="image" lido:type="local">59870</lido:resourceID>
            <lido:resourceRepresentation lido:type="image_thumb">
               <lido:linkResource lido:formatResource="image/jpeg">https://berlin.museum-digital.de/data/berlin/images/21/86350-ii_9526_i/johannes_hartmann_konsolu/100h_johannes-hartmann-konsoluhr-spaetes-19-jahrhundert-inv-nr-ii-9526-i-86350-6.jpg</lido:linkResource>
            </lido:resourceRepresentation>
            <lido:resourceRepresentation lido:type="image_preview">
               <lido:linkResource lido:formatResource="image/jpeg">https://berlin.museum-digital.de/data/berlin/images/21/86350-ii_9526_i/johannes_hartmann_konsolu/200w_johannes-hartmann-konsoluhr-spaetes-19-jahrhundert-inv-nr-ii-9526-i-86350-6.jpg</lido:linkResource>
            </lido:resourceRepresentation>
            <lido:resourceRepresentation lido:type="http://terminology.lido-schema.org/lido00464">
               <lido:linkResource lido:formatResource="image/jpeg">https://berlin.museum-digital.de/data/berlin/images/21/86350-ii_9526_i/johannes_hartmann_konsolu/johannes-hartmann-konsoluhr-spaetes-19-jahrhundert-inv-nr-ii-9526-i-86350-6.jpg</lido:linkResource>
            </lido:resourceRepresentation>
            <lido:resourceType>
               <lido:term>image</lido:term>
            </lido:resourceType>
            <lido:resourceSource lido:type="creator">
               <lido:legalBodyName>
                  <lido:appellationValue>Oliver Ziebe, Berlin (2020)</lido:appellationValue>
               </lido:legalBodyName>
            </lido:resourceSource>
            <lido:rightsResource>
               <lido:rightsType>
                  <lido:conceptID lido:type="uri">https://creativecommons.org/licenses/by/4.0/</lido:conceptID>
                  <lido:term>CC BY 4.0</lido:term>
               </lido:rightsType>
               <lido:rightsHolder>
                  <lido:legalBodyName>
                     <lido:appellationValue>Stiftung Stadtmuseum Berlin</lido:appellationValue>
                  </lido:legalBodyName>
               </lido:rightsHolder>
            </lido:rightsResource>
         </lido:resourceSet>
         <lido:resourceSet lido:sortorder="6">
            <lido:resourceID lido:source="image" lido:type="local">59869</lido:resourceID>
            <lido:resourceRepresentation lido:type="image_thumb">
               <lido:linkResource lido:formatResource="image/jpeg">https://berlin.museum-digital.de/data/berlin/images/21/86350-ii_9526_i/johannes_hartmann_konsolu/100h_johannes-hartmann-konsoluhr-spaetes-19-jahrhundert-inv-nr-ii-9526-i-86350-5.jpg</lido:linkResource>
            </lido:resourceRepresentation>
            <lido:resourceRepresentation lido:type="image_preview">
               <lido:linkResource lido:formatResource="image/jpeg">https://berlin.museum-digital.de/data/berlin/images/21/86350-ii_9526_i/johannes_hartmann_konsolu/200w_johannes-hartmann-konsoluhr-spaetes-19-jahrhundert-inv-nr-ii-9526-i-86350-5.jpg</lido:linkResource>
            </lido:resourceRepresentation>
            <lido:resourceRepresentation lido:type="http://terminology.lido-schema.org/lido00464">
               <lido:linkResource lido:formatResource="image/jpeg">https://berlin.museum-digital.de/data/berlin/images/21/86350-ii_9526_i/johannes_hartmann_konsolu/johannes-hartmann-konsoluhr-spaetes-19-jahrhundert-inv-nr-ii-9526-i-86350-5.jpg</lido:linkResource>
            </lido:resourceRepresentation>
            <lido:resourceType>
               <lido:term>image</lido:term>
            </lido:resourceType>
            <lido:resourceSource lido:type="creator">
               <lido:legalBodyName>
                  <lido:appellationValue>Oliver Ziebe, Berlin (2020)</lido:appellationValue>
               </lido:legalBodyName>
            </lido:resourceSource>
            <lido:rightsResource>
               <lido:rightsType>
                  <lido:conceptID lido:type="uri">https://creativecommons.org/licenses/by/4.0/</lido:conceptID>
                  <lido:term>CC BY 4.0</lido:term>
               </lido:rightsType>
               <lido:rightsHolder>
                  <lido:legalBodyName>
                     <lido:appellationValue>Stiftung Stadtmuseum Berlin</lido:appellationValue>
                  </lido:legalBodyName>
               </lido:rightsHolder>
            </lido:rightsResource>
         </lido:resourceSet>
         <lido:resourceSet lido:sortorder="7">
            <lido:resourceID lido:source="image" lido:type="local">59874</lido:resourceID>
            <lido:resourceRepresentation lido:type="image_thumb">
               <lido:linkResource lido:formatResource="image/jpeg">https://berlin.museum-digital.de/data/berlin/images/21/86350-ii_9526_i/johannes_hartmann_konsolu/100h_johannes-hartmann-konsoluhr-spaetes-19-jahrhundert-inv-nr-ii-9526-i-86350-10.jpg</lido:linkResource>
            </lido:resourceRepresentation>
            <lido:resourceRepresentation lido:type="image_preview">
               <lido:linkResource lido:formatResource="image/jpeg">https://berlin.museum-digital.de/data/berlin/images/21/86350-ii_9526_i/johannes_hartmann_konsolu/200w_johannes-hartmann-konsoluhr-spaetes-19-jahrhundert-inv-nr-ii-9526-i-86350-10.jpg</lido:linkResource>
            </lido:resourceRepresentation>
            <lido:resourceRepresentation lido:type="http://terminology.lido-schema.org/lido00464">
               <lido:linkResource lido:formatResource="image/jpeg">https://berlin.museum-digital.de/data/berlin/images/21/86350-ii_9526_i/johannes_hartmann_konsolu/johannes-hartmann-konsoluhr-spaetes-19-jahrhundert-inv-nr-ii-9526-i-86350-10.jpg</lido:linkResource>
            </lido:resourceRepresentation>
            <lido:resourceType>
               <lido:term>image</lido:term>
            </lido:resourceType>
            <lido:resourceSource lido:type="creator">
               <lido:legalBodyName>
                  <lido:appellationValue>Oliver Ziebe, Berlin (2020)</lido:appellationValue>
               </lido:legalBodyName>
            </lido:resourceSource>
            <lido:rightsResource>
               <lido:rightsType>
                  <lido:conceptID lido:type="uri">https://creativecommons.org/licenses/by/4.0/</lido:conceptID>
                  <lido:term>CC BY 4.0</lido:term>
               </lido:rightsType>
               <lido:rightsHolder>
                  <lido:legalBodyName>
                     <lido:appellationValue>Stiftung Stadtmuseum Berlin</lido:appellationValue>
                  </lido:legalBodyName>
               </lido:rightsHolder>
            </lido:rightsResource>
         </lido:resourceSet>
         <lido:resourceSet lido:sortorder="8">
            <lido:resourceID lido:source="image" lido:type="local">59873</lido:resourceID>
            <lido:resourceRepresentation lido:type="image_thumb">
               <lido:linkResource lido:formatResource="image/jpeg">https://berlin.museum-digital.de/data/berlin/images/21/86350-ii_9526_i/johannes_hartmann_konsolu/100h_johannes-hartmann-konsoluhr-spaetes-19-jahrhundert-inv-nr-ii-9526-i-86350-9.jpg</lido:linkResource>
            </lido:resourceRepresentation>
            <lido:resourceRepresentation lido:type="image_preview">
               <lido:linkResource lido:formatResource="image/jpeg">https://berlin.museum-digital.de/data/berlin/images/21/86350-ii_9526_i/johannes_hartmann_konsolu/200w_johannes-hartmann-konsoluhr-spaetes-19-jahrhundert-inv-nr-ii-9526-i-86350-9.jpg</lido:linkResource>
            </lido:resourceRepresentation>
            <lido:resourceRepresentation lido:type="http://terminology.lido-schema.org/lido00464">
               <lido:linkResource lido:formatResource="image/jpeg">https://berlin.museum-digital.de/data/berlin/images/21/86350-ii_9526_i/johannes_hartmann_konsolu/johannes-hartmann-konsoluhr-spaetes-19-jahrhundert-inv-nr-ii-9526-i-86350-9.jpg</lido:linkResource>
            </lido:resourceRepresentation>
            <lido:resourceType>
               <lido:term>image</lido:term>
            </lido:resourceType>
            <lido:resourceSource lido:type="creator">
               <lido:legalBodyName>
                  <lido:appellationValue>Oliver Ziebe, Berlin (2020)</lido:appellationValue>
               </lido:legalBodyName>
            </lido:resourceSource>
            <lido:rightsResource>
               <lido:rightsType>
                  <lido:conceptID lido:type="uri">https://creativecommons.org/licenses/by/4.0/</lido:conceptID>
                  <lido:term>CC BY 4.0</lido:term>
               </lido:rightsType>
               <lido:rightsHolder>
                  <lido:legalBodyName>
                     <lido:appellationValue>Stiftung Stadtmuseum Berlin</lido:appellationValue>
                  </lido:legalBodyName>
               </lido:rightsHolder>
            </lido:rightsResource>
         </lido:resourceSet>
         <lido:resourceSet lido:sortorder="9">
            <lido:resourceID lido:source="image" lido:type="local">59871</lido:resourceID>
            <lido:resourceRepresentation lido:type="image_thumb">
               <lido:linkResource lido:formatResource="image/jpeg">https://berlin.museum-digital.de/data/berlin/images/21/86350-ii_9526_i/johannes_hartmann_konsolu/100h_johannes-hartmann-konsoluhr-spaetes-19-jahrhundert-inv-nr-ii-9526-i-86350-7.jpg</lido:linkResource>
            </lido:resourceRepresentation>
            <lido:resourceRepresentation lido:type="image_preview">
               <lido:linkResource lido:formatResource="image/jpeg">https://berlin.museum-digital.de/data/berlin/images/21/86350-ii_9526_i/johannes_hartmann_konsolu/200w_johannes-hartmann-konsoluhr-spaetes-19-jahrhundert-inv-nr-ii-9526-i-86350-7.jpg</lido:linkResource>
            </lido:resourceRepresentation>
            <lido:resourceRepresentation lido:type="http://terminology.lido-schema.org/lido00464">
               <lido:linkResource lido:formatResource="image/jpeg">https://berlin.museum-digital.de/data/berlin/images/21/86350-ii_9526_i/johannes_hartmann_konsolu/johannes-hartmann-konsoluhr-spaetes-19-jahrhundert-inv-nr-ii-9526-i-86350-7.jpg</lido:linkResource>
            </lido:resourceRepresentation>
            <lido:resourceType>
               <lido:term>image</lido:term>
            </lido:resourceType>
            <lido:resourceSource lido:type="creator">
               <lido:legalBodyName>
                  <lido:appellationValue>Oliver Ziebe, Berlin (2020)</lido:appellationValue>
               </lido:legalBodyName>
            </lido:resourceSource>
            <lido:rightsResource>
               <lido:rightsType>
                  <lido:conceptID lido:type="uri">https://creativecommons.org/licenses/by/4.0/</lido:conceptID>
                  <lido:term>CC BY 4.0</lido:term>
               </lido:rightsType>
               <lido:rightsHolder>
                  <lido:legalBodyName>
                     <lido:appellationValue>Stiftung Stadtmuseum Berlin</lido:appellationValue>
                  </lido:legalBodyName>
               </lido:rightsHolder>
            </lido:rightsResource>
         </lido:resourceSet>
         <lido:resourceSet lido:sortorder="10">
            <lido:resourceID lido:source="image" lido:type="local">59872</lido:resourceID>
            <lido:resourceRepresentation lido:type="image_thumb">
               <lido:linkResource lido:formatResource="image/jpeg">https://berlin.museum-digital.de/data/berlin/images/21/86350-ii_9526_i/johannes_hartmann_konsolu/100h_johannes-hartmann-konsoluhr-spaetes-19-jahrhundert-inv-nr-ii-9526-i-86350-8.jpg</lido:linkResource>
            </lido:resourceRepresentation>
            <lido:resourceRepresentation lido:type="image_preview">
               <lido:linkResource lido:formatResource="image/jpeg">https://berlin.museum-digital.de/data/berlin/images/21/86350-ii_9526_i/johannes_hartmann_konsolu/200w_johannes-hartmann-konsoluhr-spaetes-19-jahrhundert-inv-nr-ii-9526-i-86350-8.jpg</lido:linkResource>
            </lido:resourceRepresentation>
            <lido:resourceRepresentation lido:type="http://terminology.lido-schema.org/lido00464">
               <lido:linkResource lido:formatResource="image/jpeg">https://berlin.museum-digital.de/data/berlin/images/21/86350-ii_9526_i/johannes_hartmann_konsolu/johannes-hartmann-konsoluhr-spaetes-19-jahrhundert-inv-nr-ii-9526-i-86350-8.jpg</lido:linkResource>
            </lido:resourceRepresentation>
            <lido:resourceType>
               <lido:term>image</lido:term>
            </lido:resourceType>
            <lido:resourceSource lido:type="creator">
               <lido:legalBodyName>
                  <lido:appellationValue>Oliver Ziebe, Berlin (2020)</lido:appellationValue>
               </lido:legalBodyName>
            </lido:resourceSource>
            <lido:rightsResource>
               <lido:rightsType>
                  <lido:conceptID lido:type="uri">https://creativecommons.org/licenses/by/4.0/</lido:conceptID>
                  <lido:term>CC BY 4.0</lido:term>
               </lido:rightsType>
               <lido:rightsHolder>
                  <lido:legalBodyName>
                     <lido:appellationValue>Stiftung Stadtmuseum Berlin</lido:appellationValue>
                  </lido:legalBodyName>
               </lido:rightsHolder>
            </lido:rightsResource>
         </lido:resourceSet>
         <lido:resourceSet lido:sortorder="11">
            <lido:resourceID lido:source="image" lido:type="local">59875</lido:resourceID>
            <lido:resourceRepresentation lido:type="image_thumb">
               <lido:linkResource lido:formatResource="image/jpeg">https://berlin.museum-digital.de/data/berlin/images/21/86350-ii_9526_i/johannes_hartmann_konsolu/100h_johannes-hartmann-konsoluhr-spaetes-19-jahrhundert-inv-nr-ii-9526-i-86350-11.jpg</lido:linkResource>
            </lido:resourceRepresentation>
            <lido:resourceRepresentation lido:type="image_preview">
               <lido:linkResource lido:formatResource="image/jpeg">https://berlin.museum-digital.de/data/berlin/images/21/86350-ii_9526_i/johannes_hartmann_konsolu/200w_johannes-hartmann-konsoluhr-spaetes-19-jahrhundert-inv-nr-ii-9526-i-86350-11.jpg</lido:linkResource>
            </lido:resourceRepresentation>
            <lido:resourceRepresentation lido:type="http://terminology.lido-schema.org/lido00464">
               <lido:linkResource lido:formatResource="image/jpeg">https://berlin.museum-digital.de/data/berlin/images/21/86350-ii_9526_i/johannes_hartmann_konsolu/johannes-hartmann-konsoluhr-spaetes-19-jahrhundert-inv-nr-ii-9526-i-86350-11.jpg</lido:linkResource>
            </lido:resourceRepresentation>
            <lido:resourceType>
               <lido:term>image</lido:term>
            </lido:resourceType>
            <lido:resourceSource lido:type="creator">
               <lido:legalBodyName>
                  <lido:appellationValue>Oliver Ziebe, Berlin (2020)</lido:appellationValue>
               </lido:legalBodyName>
            </lido:resourceSource>
            <lido:rightsResource>
               <lido:rightsType>
                  <lido:conceptID lido:type="uri">https://creativecommons.org/licenses/by/4.0/</lido:conceptID>
                  <lido:term>CC BY 4.0</lido:term>
               </lido:rightsType>
               <lido:rightsHolder>
                  <lido:legalBodyName>
                     <lido:appellationValue>Stiftung Stadtmuseum Berlin</lido:appellationValue>
                  </lido:legalBodyName>
               </lido:rightsHolder>
            </lido:rightsResource>
         </lido:resourceSet>
      </lido:resourceWrap>
   </lido:administrativeMetadata>
</lido:lido>

